<?xml version = '1.0' encoding = 'UTF-8'?>
<Diagram class="oracle.dbtools.crest.swingui.relational.DPVRelational" name="DWH" id="082DCF21-6640-5422-3C70-B1FAC15CC3FC">
<createdBy>Novaz</createdBy>
<modifiedBy>Novaz</modifiedBy>
<createdTime>2024-01-12 12:35:55 UTC</createdTime>
<autoRoute>false</autoRoute>
<boxInbox>true</boxInbox>
<showLegend>false</showLegend>
<showLabels>false</showLabels>
<showRelAttributes>false</showRelAttributes>
<gridEnabled>false</gridEnabled>
<showGrid>false</showGrid>
<diagramColor>-1</diagramColor>
<display>false</display>
<notation>1</notation>
<objectViews>
<OView class="oracle.dbtools.crest.swingui.relational.TVTable" oid="055C2983-130D-9671-1B74-C46F3AFFDEBD" otype="Table" vid="F81850BE-AE6F-DDA4-650D-9262E582EF54">
<hideElementsInCurrentOnly>false</hideElementsInCurrentOnly>
<bounds x="228" y="626" width="344" height="125"/>
</OView>
<OView class="oracle.dbtools.crest.swingui.relational.TVTable" oid="1576B0E2-7F0A-7487-7407-62F3289D0B71" otype="Table" vid="55B6AE81-A76B-DB9E-88C0-81537254AB3F">
<hideElementsInCurrentOnly>false</hideElementsInCurrentOnly>
<bounds x="266" y="62" width="304" height="110"/>
</OView>
<OView class="oracle.dbtools.crest.swingui.relational.TVTable" oid="7272BCA9-DB0B-4DDC-4C40-7DB0F7E2F366" otype="Table" vid="021CBFFF-2DE7-4CA8-D820-FB04B10B96FF">
<hideElementsInCurrentOnly>false</hideElementsInCurrentOnly>
<bounds x="1786" y="325" width="434" height="161"/>
</OView>
<OView class="oracle.dbtools.crest.swingui.relational.TVTable" oid="A7B0D4FA-E7E9-F323-B7C1-1FD4248E1C8A" otype="Table" vid="3F82B78C-1EB6-FBED-55D4-17A854EE4135">
<hideElementsInCurrentOnly>false</hideElementsInCurrentOnly>
<bounds x="100" y="347" width="342" height="110"/>
</OView>
<OView class="oracle.dbtools.crest.swingui.relational.TVTable" oid="A9C2756F-4DE7-66CA-F8D2-2BD22B7BE86B" otype="Table" vid="BF27A403-12C1-90D1-7796-97E781181918">
<hideElementsInCurrentOnly>false</hideElementsInCurrentOnly>
<bounds x="880" y="708" width="446" height="164"/>
</OView>
<OView class="oracle.dbtools.crest.swingui.relational.TVTable" oid="C10522F1-31A4-FC1A-D2DC-AA45E480EC5A" otype="Table" vid="E7CDEC6E-02BB-2847-70D4-54BCD38FA872">
<hideElementsInCurrentOnly>false</hideElementsInCurrentOnly>
<bounds x="1569" y="65" width="397" height="133"/>
</OView>
<OView class="oracle.dbtools.crest.swingui.relational.TVTable" oid="D7782615-E49F-E820-50B7-A5A732233FB1" otype="Table" vid="AB2510C0-1ABE-BFAE-708C-27DC362EDB7B">
<hideElementsInCurrentOnly>false</hideElementsInCurrentOnly>
<bounds x="931" y="10" width="345" height="132"/>
</OView>
<OView class="oracle.dbtools.crest.swingui.relational.TVTable" oid="DD3B9639-45F3-D8CA-9763-5AE97210472A" otype="Table" vid="06508CFE-E265-2F40-8094-78D2F43707AC">
<hideElementsInCurrentOnly>false</hideElementsInCurrentOnly>
<bounds x="881" y="233" width="452" height="348"/>
<useDefaultColor>false</useDefaultColor>
<backgroundColor>-13369345</backgroundColor>
<foregroundColor>-16776961</foregroundColor>
</OView>
<OView class="oracle.dbtools.crest.swingui.relational.TVTable" oid="FA6D2F40-E2DC-2F1F-08E5-89ACF460A84A" otype="Table" vid="E3B02889-CCAD-D505-A9F0-F0558611DA1D">
<hideElementsInCurrentOnly>false</hideElementsInCurrentOnly>
<bounds x="1597" y="621" width="366" height="160"/>
</OView>
</objectViews>
<connectors>
<Connector class="oracle.dbtools.crest.swingui.relational.TVFKRelation" oid="38E7A0AF-249F-72E2-B9B8-6825E0B02FEF" otype="FKIndexAssociation" vid_source="BF27A403-12C1-90D1-7796-97E781181918" vid_target="06508CFE-E265-2F40-8094-78D2F43707AC">
<hideElementsInCurrentOnly>false</hideElementsInCurrentOnly>
<backgroundColor>-16777216</backgroundColor>
<lineWidth>1</lineWidth>
<points>
<point x="1103" y="708"/>
<point x="1103" y="581"/>
</points>
</Connector>
<Connector class="oracle.dbtools.crest.swingui.relational.TVFKRelation" oid="7F5F547F-7A17-13CC-6D15-2A75AA491F74" otype="FKIndexAssociation" vid_source="021CBFFF-2DE7-4CA8-D820-FB04B10B96FF" vid_target="06508CFE-E265-2F40-8094-78D2F43707AC">
<hideElementsInCurrentOnly>false</hideElementsInCurrentOnly>
<backgroundColor>-16777216</backgroundColor>
<lineWidth>1</lineWidth>
<points>
<point x="1786" y="405"/>
<point x="1333" y="405"/>
</points>
</Connector>
<Connector class="oracle.dbtools.crest.swingui.relational.TVFKRelation" oid="C5065591-B0BB-6B16-28D7-7594BF407B79" otype="FKIndexAssociation" vid_source="3F82B78C-1EB6-FBED-55D4-17A854EE4135" vid_target="06508CFE-E265-2F40-8094-78D2F43707AC">
<hideElementsInCurrentOnly>false</hideElementsInCurrentOnly>
<backgroundColor>-16777216</backgroundColor>
<lineWidth>1</lineWidth>
<points>
<point x="442" y="402"/>
<point x="881" y="402"/>
</points>
</Connector>
<Connector class="oracle.dbtools.crest.swingui.relational.TVFKRelation" oid="CCAB7CF8-5D15-6E7B-9B43-D4561C50EAE8" otype="FKIndexAssociation" vid_source="E3B02889-CCAD-D505-A9F0-F0558611DA1D" vid_target="06508CFE-E265-2F40-8094-78D2F43707AC">
<hideElementsInCurrentOnly>false</hideElementsInCurrentOnly>
<backgroundColor>-16777216</backgroundColor>
<lineWidth>1</lineWidth>
<points>
<point x="1597" y="621"/>
<point x="1333" y="505"/>
</points>
</Connector>
<Connector class="oracle.dbtools.crest.swingui.relational.TVFKRelation" oid="E1EA6C48-E54F-B278-2CEE-347615614864" otype="FKIndexAssociation" vid_source="AB2510C0-1ABE-BFAE-708C-27DC362EDB7B" vid_target="06508CFE-E265-2F40-8094-78D2F43707AC">
<hideElementsInCurrentOnly>false</hideElementsInCurrentOnly>
<backgroundColor>-16777216</backgroundColor>
<lineWidth>1</lineWidth>
<points>
<point x="1103" y="142"/>
<point x="1103" y="233"/>
</points>
</Connector>
<Connector class="oracle.dbtools.crest.swingui.relational.TVFKRelation" oid="E5DC402D-176A-E6AE-565C-D185E7C9374E" otype="FKIndexAssociation" vid_source="F81850BE-AE6F-DDA4-650D-9262E582EF54" vid_target="06508CFE-E265-2F40-8094-78D2F43707AC">
<hideElementsInCurrentOnly>false</hideElementsInCurrentOnly>
<backgroundColor>-16777216</backgroundColor>
<lineWidth>1</lineWidth>
<points>
<point x="556" y="626"/>
<point x="881" y="496"/>
</points>
</Connector>
<Connector class="oracle.dbtools.crest.swingui.relational.TVFKRelation" oid="E8557BC3-CC2F-7609-0821-510474CDF54A" otype="FKIndexAssociation" vid_source="55B6AE81-A76B-DB9E-88C0-81537254AB3F" vid_target="06508CFE-E265-2F40-8094-78D2F43707AC">
<hideElementsInCurrentOnly>false</hideElementsInCurrentOnly>
<backgroundColor>-16777216</backgroundColor>
<lineWidth>1</lineWidth>
<points>
<point x="548" y="172"/>
<point x="881" y="311"/>
</points>
</Connector>
<Connector class="oracle.dbtools.crest.swingui.relational.TVFKRelation" oid="F72152C3-3D5D-EFDA-5262-EA3826CF0BB4" otype="FKIndexAssociation" vid_source="E7CDEC6E-02BB-2847-70D4-54BCD38FA872" vid_target="06508CFE-E265-2F40-8094-78D2F43707AC">
<hideElementsInCurrentOnly>false</hideElementsInCurrentOnly>
<backgroundColor>-16777216</backgroundColor>
<lineWidth>1</lineWidth>
<points>
<point x="1608" y="198"/>
<point x="1333" y="312"/>
</points>
</Connector>
</connectors>
</Diagram>
